msunpv/__init__.py
msunpv/const.py
msunpv/data.py
msunpv/exceptions.py
msunpv/read.py
msunpv/webconnect.py
msunpv-0.2.0.dist-info/licenses/LICENSE
msunpv-0.2.0.dist-info/METADATA
msunpv-0.2.0.dist-info/WHEEL
msunpv-0.2.0.dist-info/top_level.txt
msunpv-0.2.0.dist-info/RECORD
