Metadata-Version: 2.4
Name: msunpv
Version: 0.2.0
Summary: Library to interface an msunpv devices.
Author-email: franck VANHOUCKE <vanhoucke.franck@free.fr>
License-Expression: Apache-2.0
Project-URL: Homepage, https://github.com/thanatos-vf-2000/msunpv
Project-URL: Issues, https://github.com/thanatos-vf-2000/msunpv
Project-URL: Documents, https://thanatos-vf-2000.github.io/msunpv/
Classifier: Programming Language :: Python :: 3 :: Only
Classifier: Programming Language :: Python :: 3.9
Classifier: Programming Language :: Python :: 3.10
Classifier: Programming Language :: Python :: 3.11
Classifier: Programming Language :: Python :: 3.12
Classifier: Programming Language :: Python :: 3.13
Classifier: Programming Language :: Python :: 3.14
Requires-Python: >=3.9
License-File: LICENSE
Requires-Dist: aiohttp<4,>=3
Requires-Dist: xmltodict
Dynamic: license-file
